sipiiiii/__init__.py
sipiiiii/main.py
sipiiiii/app/__init__.py
sipiiiii/app/core.py
sipiiiii/app/new_app.py
sipiiiii/app/version.py
sipiiiii/app/utils/HttpSDK.py
sipiiiii/app/utils/Tools.py
sipiiiii/app/utils/ZipFileTool.py
sipiiiii/app/utils/__init__.py
sipiiiii/app/utils/config.py
sipiiiii/app/utils/formatConversion.py
sipiiiii-1.2.0.dist-info/METADATA
sipiiiii-1.2.0.dist-info/WHEEL
sipiiiii-1.2.0.dist-info/entry_points.txt
sipiiiii-1.2.0.dist-info/top_level.txt
sipiiiii-1.2.0.dist-info/RECORD
