Metadata-Version: 2.1
Name: sipiiiii
Version: 1.2.0
Summary: sipiiiii定位为简单易用的云应用托管平台
Home-page: http://www.depl.run/
Author: sipiiiii@admin
Author-email: DeplRun <sipiiiii@example.com>
Project-URL: Homepage, http://www.depl.run/
Project-URL: Bug Tracker, http://www.depl.run/
Classifier: Programming Language :: Python :: 3
Classifier: License :: OSI Approved :: MIT License
Classifier: Operating System :: OS Independent
Requires-Python: >=3.9
Requires-Dist: httpx
Requires-Dist: prettytable (==3.7.0)
Requires-Dist: jinja2
Requires-Dist: requests
Requires-Dist: requests-toolbelt
Requires-Dist: xmltodict
Requires-Dist: validators
Requires-Dist: pathlib
Requires-Dist: jsonpath
Requires-Dist: pyyaml
